odoo9_addon_account_bank_statement_import_move_line-9.0.1.0.0-py2.7-nspkg.pth
odoo9_addon_account_bank_statement_import_move_line-9.0.1.0.0.dist-info/DESCRIPTION.rst
odoo9_addon_account_bank_statement_import_move_line-9.0.1.0.0.dist-info/METADATA
odoo9_addon_account_bank_statement_import_move_line-9.0.1.0.0.dist-info/RECORD
odoo9_addon_account_bank_statement_import_move_line-9.0.1.0.0.dist-info/WHEEL
odoo9_addon_account_bank_statement_import_move_line-9.0.1.0.0.dist-info/metadata.json
odoo9_addon_account_bank_statement_import_move_line-9.0.1.0.0.dist-info/namespace_packages.txt
odoo9_addon_account_bank_statement_import_move_line-9.0.1.0.0.dist-info/top_level.txt
odoo_addons/account_bank_statement_import_move_line/README.rst
odoo_addons/account_bank_statement_import_move_line/__init__.py
odoo_addons/account_bank_statement_import_move_line/__openerp__.py
odoo_addons/account_bank_statement_import_move_line/i18n/es.po
odoo_addons/account_bank_statement_import_move_line/models/__init__.py
odoo_addons/account_bank_statement_import_move_line/models/account_move_line.py
odoo_addons/account_bank_statement_import_move_line/static/description/icon.png
odoo_addons/account_bank_statement_import_move_line/tests/__init__.py
odoo_addons/account_bank_statement_import_move_line/tests/test_account_bank_statement_import_move_line.py
odoo_addons/account_bank_statement_import_move_line/views/account_bank_statement_view.xml
odoo_addons/account_bank_statement_import_move_line/wizards/__init__.py
odoo_addons/account_bank_statement_import_move_line/wizards/account_statement_line_create.py
odoo_addons/account_bank_statement_import_move_line/wizards/account_statement_line_create_view.xml
